imdbpie/__init__.py
imdbpie/auth.py
imdbpie/constants.py
imdbpie/exceptions.py
imdbpie/facade.py
imdbpie/imdbpie.py
imdbpie/objects.py
imdbpie-5.6.5.dist-info/LICENSE
imdbpie-5.6.5.dist-info/METADATA
imdbpie-5.6.5.dist-info/WHEEL
imdbpie-5.6.5.dist-info/top_level.txt
imdbpie-5.6.5.dist-info/RECORD
