Metadata-Version: 2.1
Name: imdbpie
Version: 5.6.5
Summary: Python IMDB client using the IMDB json web service made available for their iOS app.
Home-page: https://code.richard.do/richardARPANET/imdb-pie/
Author: Richard O'Dwyer
Author-email: richard@richard.do
License: Apache 2.0
Classifier: Intended Audience :: Developers
Classifier: Operating System :: OS Independent
Classifier: Programming Language :: Python
Classifier: Programming Language :: Python :: 2
Classifier: Programming Language :: Python :: 3
Classifier: Topic :: Internet :: WWW/HTTP
License-File: LICENSE
Requires-Dist: requests (<3.0.0,>=0.10)
Requires-Dist: six (<2.0.0,>=1.0.0)
Requires-Dist: wheel (>=0.38.0)
Requires-Dist: boto (>=2.48.0)
Requires-Dist: python-dateutil (<3.0.0,>=2.6.1)
Requires-Dist: diskcache (<3.0.0,>=2.9.0)
Requires-Dist: setuptools (>=65.5.1)
Requires-Dist: attrs (<19.0.0,>=18.1.0)
Requires-Dist: trans (<3.0.0,>=2.1.0)
